mdsearch/__init__.py
mdsearch/searcher.py
mdsearch/Similarity/__init__.py
mdsearch/Similarity/sentence_similarity.py
mdsearch/Similarity/similarity_server.py
mdsearch/Similarity/similarity_test.py
mdsearch-0.0.9.dist-info/LICENSE
mdsearch-0.0.9.dist-info/METADATA
mdsearch-0.0.9.dist-info/WHEEL
mdsearch-0.0.9.dist-info/top_level.txt
mdsearch-0.0.9.dist-info/RECORD
