Metadata-Version: 2.1
Name: mdsearch
Version: 0.0.9
Summary: mdsearch is a python package for paper search
Home-page: https://github.com/lydia07/mdsearch
Author: Low-level Maseter Do Search
Author-email: 3120201103@bit.edu.cn
License: UNKNOWN
Platform: UNKNOWN
Classifier: Programming Language :: Python :: 3
Classifier: License :: OSI Approved :: MIT License
Classifier: Operating System :: OS Independent
Classifier: Topic :: Software Development :: Libraries
Classifier: Topic :: Software Development :: Libraries :: Python Modules
Classifier: Intended Audience :: Developers
Requires-Python: >=3.6
Requires-Dist: elasticsearch5
Requires-Dist: flask (==1.1.2)
